setup.py
django_registration_extended_backend.egg-info/PKG-INFO
django_registration_extended_backend.egg-info/SOURCES.txt
django_registration_extended_backend.egg-info/dependency_links.txt
django_registration_extended_backend.egg-info/requires.txt
django_registration_extended_backend.egg-info/top_level.txt
extendedregistrationbackend/__init__.py
extendedregistrationbackend/forms.py
extendedregistrationbackend/extended/__init__.py
extendedregistrationbackend/extended/urls.py