Metadata-Version: 1.0
Name: django-registration-extended-backend
Version: 0.1.a2
Summary: Backend for django registration that sends email in HTML and does email normalization
Home-page: https://github.com/huseyinyilmaz/django-registration-extended-backend
Author: Huseyin Yilmaz
Author-email: me@yilmazhuseyin.com
License: GPLv3
Keywords: django registration django-registration
Platform: UNKNOWN
